README.md
setup.py
hocr_parser/__init__.py
hocr_parser/parser.py
hocr_parser.egg-info/PKG-INFO
hocr_parser.egg-info/SOURCES.txt
hocr_parser.egg-info/dependency_links.txt
hocr_parser.egg-info/requires.txt
hocr_parser.egg-info/top_level.txt
test/__init__.py
test/parsingHocrToJson.py