Metadata-Version: 1.0
Name: hocr-parser
Version: 0.0.5
Summary: This is a package for get json file from hocr file
Home-page: UNKNOWN
Author: UNKNOWN
Author-email: originman@bluehack.net
License: UNKNOWN
Keywords: hocr,hocr-parser
Platform: UNKNOWN
